svms/__init__.py
svms/main.py
svms-0.0.2.dist-info/LICENSE
svms-0.0.2.dist-info/METADATA
svms-0.0.2.dist-info/WHEEL
svms-0.0.2.dist-info/RECORD
